microbiome/__init__.py
microbiome/dataset.py
microbiome/enumerations.py
microbiome/statistical_analysis.py
microbiome/trajectory.py
microbiome_toolbox-1.0.2.dist-info/LICENSE
microbiome_toolbox-1.0.2.dist-info/METADATA
microbiome_toolbox-1.0.2.dist-info/WHEEL
microbiome_toolbox-1.0.2.dist-info/top_level.txt
microbiome_toolbox-1.0.2.dist-info/RECORD
