Metadata-Version: 2.1
Name: microbiome-toolbox
Version: 1.0.2
Summary: Microbiome Toolbox
Home-page: https://github.com/JelenaBanjac/microbiome-toolbox
Author: Jelena Banjac, Shaillay Kumar Dogra, Norbert Sprenger
Author-email: msjelenabanjac@gmail.com, ShaillayKumar.Dogra@rd.nestle.com, norbert.sprenger@rdls.nestle.com
Maintainer: Jelena Banjac
Maintainer-email: msjelenabanjac@gmail.com
License: UNKNOWN
Platform: UNKNOWN
Classifier: Programming Language :: Python :: 3
Classifier: License :: OSI Approved :: MIT License
Classifier: Operating System :: OS Independent
Requires-Python: >=3.6
Requires-Dist: seaborn
Requires-Dist: ipyvolume
Requires-Dist: xgboost
Requires-Dist: certifi
Requires-Dist: cycler
Requires-Dist: matplotlib
Requires-Dist: pyparsing
Requires-Dist: ipykernel
Requires-Dist: ipython
Requires-Dist: ipython-genutils
Requires-Dist: jedi
Requires-Dist: joblib
Requires-Dist: jupyter-client
Requires-Dist: jupyter-core
Requires-Dist: numpy
Requires-Dist: pandas
Requires-Dist: parso
Requires-Dist: pickleshare
Requires-Dist: pip
Requires-Dist: prompt-toolkit
Requires-Dist: pygments
Requires-Dist: python-dateutil
Requires-Dist: scikit-learn
Requires-Dist: scipy
Requires-Dist: setuptools
Requires-Dist: six
Requires-Dist: threadpoolctl
Requires-Dist: tornado
Requires-Dist: traitlets
Requires-Dist: wheel
Requires-Dist: dash (==2.0.0)
Requires-Dist: diskcache
Requires-Dist: multiprocess
Requires-Dist: psutil
Requires-Dist: dash-renderer
Requires-Dist: dash-table
Requires-Dist: dash-uploader
Requires-Dist: dash-extensions
Requires-Dist: plotly
Requires-Dist: flask-caching
Requires-Dist: statsmodels
Requires-Dist: shap
Requires-Dist: tk
Requires-Dist: gunicorn
Requires-Dist: python-dotenv
Requires-Dist: natsort
Requires-Dist: umap-learn
Requires-Dist: black
Requires-Dist: isort
